genelocator/__init__.py
genelocator/__version__.py
genelocator/assets.py
genelocator/const.py
genelocator/download.py
genelocator/exception.py
genelocator/locate.py
genelocator/data/genes-grch37-gencode32-all.pickle.gz
genelocator/data/genes-grch37-gencode32-codinglike.pickle.gz
genelocator/data/genes-grch38-gencode32-all.pickle.gz
genelocator/data/genes-grch38-gencode32-codinglike.pickle.gz
GeneLocator-1.1.2.dist-info/METADATA
GeneLocator-1.1.2.dist-info/WHEEL
GeneLocator-1.1.2.dist-info/entry_points.txt
GeneLocator-1.1.2.dist-info/top_level.txt
GeneLocator-1.1.2.dist-info/RECORD
