Metadata-Version: 2.1
Name: GeneLocator
Version: 1.1.2
Summary: A library for finding the nearest gene to a genomic location
Home-page: https://github.com/pjvandehaar/genelocator
Author: Peter VandeHaar
Author-email: pjvandehaar@gmail.com
License: MIT
Platform: UNKNOWN
Classifier: Programming Language :: Python :: 3 :: Only
Classifier: Operating System :: Unix
Classifier: Operating System :: POSIX :: Linux
Classifier: Operating System :: MacOS :: MacOS X
Classifier: License :: OSI Approved :: MIT License
Classifier: Intended Audience :: Science/Research
Classifier: Topic :: Scientific/Engineering :: Bio-Informatics
Requires-Python: >=3.5
Requires-Dist: intervaltree (~=3.0)
